<?xml version="1.0" encoding="UTF-8" ?>
<!DOCTYPE mapper PUBLIC "-//mybatis.org//DTD Mapper 3.0//EN" "http://mybatis.org/dtd/mybatis-3-mapper.dtd" >
<mapper namespace="com.fh.taolijie.dao.mapper.ReviewModelMapper">
    <resultMap id="BaseResultMap" type="com.fh.taolijie.domain.ReviewModel">
        <!--
          WARNING - @mbggenerated
          This element is automatically generated by MyBatis Generator, do not modify.
        -->
        <id column="id" property="id" jdbcType="INTEGER"/>
        <result column="post_id" property="postId" jdbcType="INTEGER"/>
        <result column="member_id" property="memberId" jdbcType="INTEGER"/>
        <result column="time" property="time" jdbcType="DATE"/>
        <result column="replied_review_id" property="repliedReviewId" jdbcType="INTEGER"/>

        <result column="content" property="content" jdbcType="LONGVARCHAR"/>

        <association property="member" resultMap="com.fh.taolijie.dao.mapper.MemberModelMapper.BaseResultMap"/>
        <association property="jobPost" resultMap="com.fh.taolijie.dao.mapper.JobPostModelMapper.BaseResultMap"/>
    </resultMap>

    <sql id="Base_Column_List">
        <!--
          WARNING - @mbggenerated
          This element is automatically generated by MyBatis Generator, do not modify.
        -->
        id, post_id, member_id, time, replied_review_id, content
    </sql>
    <select id="selectByPrimaryKey" resultMap="BaseResultMap" parameterType="java.lang.Integer">
        <!--
          WARNING - @mbggenerated
          This element is automatically generated by MyBatis Generator, do not modify.
        -->
        select
        <include refid="Base_Column_List"/>
        from review re
        LEFT JOIN member mem ON mem.id = re.member_id
        LEFT JOIN job_post job WHERE job.id = re.post_id
        where id = #{id,jdbcType=INTEGER}
    </select>
    <delete id="deleteByPrimaryKey" parameterType="java.lang.Integer">
        <!--
          WARNING - @mbggenerated
          This element is automatically generated by MyBatis Generator, do not modify.
        -->
        DELETE FROM review
        WHERE id = #{id,jdbcType=INTEGER}
    </delete>
    <insert id="insert" parameterType="com.fh.taolijie.domain.ReviewModel">
        <!--
          WARNING - @mbggenerated
          This element is automatically generated by MyBatis Generator, do not modify.
        -->
        INSERT INTO review (post_id, member_id,
        time, replied_review_id, content
        )
        VALUES (#{postId,jdbcType=INTEGER}, #{memberId,jdbcType=INTEGER},
        #{time,jdbcType=DATE}, #{repliedReviewId,jdbcType=INTEGER}, #{content,jdbcType=LONGVARCHAR}
        )
    </insert>
    <insert id="insertSelective" parameterType="com.fh.taolijie.domain.ReviewModel">
        <!--
          WARNING - @mbggenerated
          This element is automatically generated by MyBatis Generator, do not modify.
        -->
        insert into review
        <trim prefix="(" suffix=")" suffixOverrides=",">
            <if test="postId != null">
                post_id,
            </if>
            <if test="memberId != null">
                member_id,
            </if>
            <if test="time != null">
                time,
            </if>
            <if test="repliedReviewId != null">
                replied_review_id,
            </if>
            <if test="content != null">
                content,
            </if>
        </trim>
        <trim prefix="values (" suffix=")" suffixOverrides=",">
            <if test="postId != null">
                #{postId,jdbcType=INTEGER},
            </if>
            <if test="memberId != null">
                #{memberId,jdbcType=INTEGER},
            </if>
            <if test="time != null">
                #{time,jdbcType=DATE},
            </if>
            <if test="repliedReviewId != null">
                #{repliedReviewId,jdbcType=INTEGER},
            </if>
            <if test="content != null">
                #{content,jdbcType=LONGVARCHAR},
            </if>
        </trim>
    </insert>
    <update id="updateByPrimaryKeySelective" parameterType="com.fh.taolijie.domain.ReviewModel">
        <!--
          WARNING - @mbggenerated
          This element is automatically generated by MyBatis Generator, do not modify.
        -->
        update review
        <set>
            <if test="postId != null">
                post_id = #{postId,jdbcType=INTEGER},
            </if>
            <if test="memberId != null">
                member_id = #{memberId,jdbcType=INTEGER},
            </if>
            <if test="time != null">
                time = #{time,jdbcType=DATE},
            </if>
            <if test="repliedReviewId != null">
                replied_review_id = #{repliedReviewId,jdbcType=INTEGER},
            </if>
            <if test="content != null">
                content = #{content,jdbcType=LONGVARCHAR},
            </if>
        </set>
        where id = #{id,jdbcType=INTEGER}
    </update>
    <update id="updateByPrimaryKey" parameterType="com.fh.taolijie.domain.ReviewModel">
        <!--
          WARNING - @mbggenerated
          This element is automatically generated by MyBatis Generator, do not modify.
        -->
        UPDATE review
        SET post_id = #{postId,jdbcType=INTEGER},
        member_id = #{memberId,jdbcType=INTEGER},
        time = #{time,jdbcType=DATE},
        replied_review_id = #{repliedReviewId,jdbcType=INTEGER},
        content = #{content,jdbcType=LONGVARCHAR}
        WHERE id = #{id,jdbcType=INTEGER}
    </update>

    <select id="getInBatch" resultMap="BaseResultMap">
        SELECT * FROM review WHERE id IN
        <foreach collection="list" close=")" open="(" separator="," item="id">#{id}</foreach>
    </select>

    <delete id="deleteInBatch">
        DELETE FROM review WHERE id IN
        <foreach collection="list" close=")" open="(" separator="," item="id">#{id}</foreach>
    </delete>

    <select id="findBy" resultMap="BaseResultMap">
        SELECT * FROM review
        <where>
            <if test="postId != null">
                post_id = #{postId,jdbcType=INTEGER}
            </if>
            <if test="memberId != null">
                AND member_id = #{memberId,jdbcType=INTEGER}
            </if>
            <if test="time != null">
                AND time = #{time,jdbcType=DATE}
            </if>
            <if test="repliedReviewId != null">
                AND replied_review_id = #{repliedReviewId,jdbcType=INTEGER}
            </if>
            <if test="content != null">
                AND content = #{content,jdbcType=LONGVARCHAR}
            </if>
        </where>
    </select>

</mapper>