<?xml version="1.0" encoding="UTF-8" ?>
<!DOCTYPE mapper PUBLIC "-//mybatis.org//DTD Mapper 3.0//EN" "http://mybatis.org/dtd/mybatis-3-mapper.dtd" >
<mapper namespace="com.fh.taolijie.dao.mapper.TljAuditModelMapper">
    <resultMap id="BaseResultMap" type="com.fh.taolijie.domain.TljAuditModel">
        <!--
          WARNING - @mbggenerated
          This element is automatically generated by MyBatis Generator, do not modify.
        -->
        <id column="id" property="id" jdbcType="INTEGER"/>
        <result column="quest_id" property="questId" jdbcType="INTEGER"/>
        <result column="quest_title" property="questTitle" jdbcType="VARCHAR"/>
        <result column="tot_amt" property="totAmt" jdbcType="INTEGER"/>
        <result column="left_amt" property="leftAmt" jdbcType="INTEGER"/>
        <result column="emp_id" property="empId" jdbcType="INTEGER"/>
        <result column="emp_username" property="empUsername" jdbcType="VARCHAR"/>
    </resultMap>
    <sql id="Base_Column_List">
        <!--
          WARNING - @mbggenerated
          This element is automatically generated by MyBatis Generator, do not modify.
        -->
        id, quest_id, quest_title, tot_amt, left_amt, emp_id, emp_username
    </sql>
    <select id="selectByPrimaryKey" resultMap="BaseResultMap" parameterType="java.lang.Integer">
        <!--
          WARNING - @mbggenerated
          This element is automatically generated by MyBatis Generator, do not modify.
        -->
        select
        <include refid="Base_Column_List"/>
        from tlj_audit
        where id = #{id,jdbcType=INTEGER}
    </select>
    <delete id="deleteByPrimaryKey" parameterType="java.lang.Integer">
        <!--
          WARNING - @mbggenerated
          This element is automatically generated by MyBatis Generator, do not modify.
        -->
        delete from tlj_audit
        where id = #{id,jdbcType=INTEGER}
    </delete>
    <insert id="insert" parameterType="com.fh.taolijie.domain.TljAuditModel">
        <!--
          WARNING - @mbggenerated
          This element is automatically generated by MyBatis Generator, do not modify.
        -->
        insert into tlj_audit (id, quest_id, quest_title,
        tot_amt, left_amt, emp_id,
        emp_username)
        values (#{id,jdbcType=INTEGER}, #{questId,jdbcType=INTEGER}, #{questTitle,jdbcType=VARCHAR},
        #{totAmt,jdbcType=INTEGER}, #{leftAmt,jdbcType=INTEGER}, #{empId,jdbcType=INTEGER},
        #{empUsername,jdbcType=VARCHAR})
    </insert>
    <insert id="insertSelective" parameterType="com.fh.taolijie.domain.TljAuditModel">
        <!--
          WARNING - @mbggenerated
          This element is automatically generated by MyBatis Generator, do not modify.
        -->
        insert into tlj_audit
        <trim prefix="(" suffix=")" suffixOverrides=",">
            <if test="id != null">
                id,
            </if>
            <if test="questId != null">
                quest_id,
            </if>
            <if test="questTitle != null">
                quest_title,
            </if>
            <if test="totAmt != null">
                tot_amt,
            </if>
            <if test="leftAmt != null">
                left_amt,
            </if>
            <if test="empId != null">
                emp_id,
            </if>
            <if test="empUsername != null">
                emp_username,
            </if>
        </trim>
        <trim prefix="values (" suffix=")" suffixOverrides=",">
            <if test="id != null">
                #{id,jdbcType=INTEGER},
            </if>
            <if test="questId != null">
                #{questId,jdbcType=INTEGER},
            </if>
            <if test="questTitle != null">
                #{questTitle,jdbcType=VARCHAR},
            </if>
            <if test="totAmt != null">
                #{totAmt,jdbcType=INTEGER},
            </if>
            <if test="leftAmt != null">
                #{leftAmt,jdbcType=INTEGER},
            </if>
            <if test="empId != null">
                #{empId,jdbcType=INTEGER},
            </if>
            <if test="empUsername != null">
                #{empUsername,jdbcType=VARCHAR},
            </if>
        </trim>
    </insert>
    <update id="updateByPrimaryKeySelective" parameterType="com.fh.taolijie.domain.TljAuditModel">
        <!--
          WARNING - @mbggenerated
          This element is automatically generated by MyBatis Generator, do not modify.
        -->
        update tlj_audit
        <set>
            <if test="questId != null">
                quest_id = #{questId,jdbcType=INTEGER},
            </if>
            <if test="questTitle != null">
                quest_title = #{questTitle,jdbcType=VARCHAR},
            </if>
            <if test="totAmt != null">
                tot_amt = #{totAmt,jdbcType=INTEGER},
            </if>
            <if test="leftAmt != null">
                left_amt = #{leftAmt,jdbcType=INTEGER},
            </if>
            <if test="empId != null">
                emp_id = #{empId,jdbcType=INTEGER},
            </if>
            <if test="empUsername != null">
                emp_username = #{empUsername,jdbcType=VARCHAR},
            </if>
        </set>
        where id = #{id,jdbcType=INTEGER}
    </update>
    <update id="updateByPrimaryKey" parameterType="com.fh.taolijie.domain.TljAuditModel">
        <!--
          WARNING - @mbggenerated
          This element is automatically generated by MyBatis Generator, do not modify.
        -->
        update tlj_audit
        set quest_id = #{questId,jdbcType=INTEGER},
        quest_title = #{questTitle,jdbcType=VARCHAR},
        tot_amt = #{totAmt,jdbcType=INTEGER},
        left_amt = #{leftAmt,jdbcType=INTEGER},
        emp_id = #{empId,jdbcType=INTEGER},
        emp_username = #{empUsername,jdbcType=VARCHAR}
        where id = #{id,jdbcType=INTEGER}
    </update>
</mapper>